{
  "nhsukie7.css": "nhsukie7-d36367ec.css",
  "nhsukie6.css": "nhsukie6-a53010a9.css",
  "nhsukie8.css": "nhsukie8-41a1000c.css",
  "print.css": "print-da503f6c.css",
  "nhsuk.css": "nhsuk-3d3f83d8.css",
  "public/js/customga.js": "public/js/customga-8d31c819.js",
  "customga.js": "customga-8d31c819.js",
  "js/customga.js": "js/customga-9978fb19.js",
  "js/analytics.js": "js/analytics-f4632fe0.js",
  "js/customwthj.js": "js/customwthj-e741988e.js",
  "js/cookiemessage.js": "js/cookiemessage-0ded11a2.js"
}